{"nums": {"py/reduce": [{"py/function": "numpy.core.multiarray._reconstruct"}, {"py/tuple": [{"py/type": "numpy.ndarray"}, {"py/tuple": [0]}, {"py/b64": "Yg==\n"}]}, {"py/tuple": [1, {"py/tuple": [10]}, {"py/id": 2}, false, {"py/b64": "KwAAAAAAAAA0AAAAAAAAAAcAAAAAAAAAGgAAAAAAAABQAAAAAAAAAAMAAAAAAAAADgAAAAAAAAAs\nAAAAAAAAABsAAAAAAAAAXgAAAAAAAAA=\n"}]}, null, null]}, "starts": {"py/reduce": [{"py/function": "numpy.core.multiarray._reconstruct"}, {"py/tuple": [{"py/type": "numpy.ndarray"}, {"py/tuple": [0]}, {"py/b64": "Yg==\n"}]}, {"py/tuple": [1, {"py/tuple": [10]}, {"py/id": 7}, false, {"py/b64": "2ccrP7HGE0B8IjSMsRcCQCHuP72kjfA/EZQPrNhSF0CCFj8Xf/QSQK5XTohrMNk/U+v6h0dQ9D/E\nrGHfsmbrPx42AhVAPxJALlQBC2pl9z8=\n"}]}, null, null]}, "it": 546, "py/object": "metalens.Metalens", "score": {"py/reduce": [{"py/function": "numpy.core.multiarray.scalar"}, {"py/tuple": [{"py/reduce": [{"py/type": "numpy.dtype"}, {"py/tuple": ["f8", 0, 1]}, {"py/tuple": [3, "<", null, null, null, -1, -1, 0]}, null, null]}, {"py/b64": "AAAAAAAAAAA=\n"}]}, null, null, null]}, "random_seed": 331, "focus": {"py/tuple": [{"py/reduce": [{"py/function": "numpy.core.multiarray.scalar"}, {"py/tuple": [{"py/reduce": [{"py/type": "numpy.dtype"}, {"py/tuple": ["i8", 0, 1]}, {"py/tuple": [3, "<", null, null, null, -1, -1, 0]}, null, null]}, {"py/b64": "AAAAAAAAAAA=\n"}]}, null, null, null]}, {"py/reduce": [{"py/function": "numpy.core.multiarray.scalar"}, {"py/tuple": [{"py/id": 2}, {"py/b64": "cBcAAAAAAAA=\n"}]}, null, null, null]}]}, "rads": {"py/reduce": [{"py/function": "numpy.core.multiarray._reconstruct"}, {"py/tuple": [{"py/type": "numpy.ndarray"}, {"py/tuple": [0]}, {"py/b64": "Yg==\n"}]}, {"py/tuple": [1, {"py/tuple": [10]}, {"py/id": 2}, false, {"py/b64": "KxsAAAAAAADADgAAAAAAAN4hAAAAAAAAHwoAAAAAAAB0FwAAAAAAAKAxAAAAAAAAfg0AAAAAAAC7\nJQAAAAAAACQgAAAAAAAAVy4AAAAAAAA=\n"}]}, null, null]}}